setup.py
lib/commonutil/__init__.py
lib/commonutil/application.py
lib/commonutil/container.py
lib/commonutil/convert.py
lib/commonutil/dmacro.py
lib/commonutil/exceptions.py
lib/commonutil/fetch.py
lib/commonutil/filefolder.py
lib/commonutil/filetimetag.py
lib/commonutil/formula.py
lib/commonutil/moduleimp.py
lib/commonutil/pathtag.py
lib/commonutil/runprogram.py
lib/commonutil/sanitize.py
lib/commonutil/statusfile.py
lib/commonutil/template.py
lib/commonutil/ticktock.py
lib/commonutil/traversal.py
lib/commonutil.egg-info/PKG-INFO
lib/commonutil.egg-info/SOURCES.txt
lib/commonutil.egg-info/dependency_links.txt
lib/commonutil.egg-info/top_level.txt
lib/commonutil/net/__init__.py
lib/commonutil/net/thrift.py
lib/commonutil/net/websocket.py
lib/commonutil/net/wsgi.py
lib/commonutil/tool/__init__.py
lib/commonutil/tool/bumprevision.py
lib/commonutil/tool/revision.py
lib/commonutil/tool/templatemarker/__init__.py
lib/commonutil/tool/templatemarker/codecomment.py
lib/commonutil/tool/vcshelper/__init__.py
lib/commonutil/tool/vcshelper/githelper.py
lib/commonutil/tool/vcshelper/mercurialhelper.py
test/test_container.py
test/test_convert.py
test/test_dmacro.py