Metadata-Version: 1.1
Name: commonutil
Version: 0.1.20
Summary: Common utility functions
Home-page: https://bitbucket.org/cheyinl/commonutil-py
Author: UNKNOWN
Author-email: UNKNOWN
License: MIT License
Platform: UNKNOWN
Classifier: Development Status :: 5 - Production/Stable
Classifier: Intended Audience :: Developers
Classifier: License :: OSI Approved :: MIT License
Classifier: Operating System :: POSIX
Classifier: Programming Language :: Python :: 2.7
